art_dl/__init__.py
art_dl/__main__.py
art_dl/cache.py
art_dl/log.py
art_dl/redirect_server.py
art_dl/sites/__init__.py
art_dl/sites/__init__.pyi
art_dl/sites/artstation.py
art_dl/sites/danbooru.py
art_dl/sites/deviantart/__init__.py
art_dl/sites/deviantart/common.py
art_dl/sites/deviantart/download.py
art_dl/sites/deviantart/register.py
art_dl/sites/deviantart/service.py
art_dl/sites/imgur.py
art_dl/sites/pixiv.py
art_dl/sites/reddit.py
art_dl/sites/twitter.py
art_dl/sites/wallhaven.py
art_dl/utils/cleanup.py
art_dl/utils/config.py
art_dl/utils/credentials.py
art_dl/utils/db.py
art_dl/utils/dirs.py
art_dl/utils/download.py
art_dl/utils/path.py
art_dl/utils/print.py
art_dl/utils/proxy.py
art_dl/utils/retry.py
art_dl/utils/url.py
art_dl-0.2.7.dist-info/entry_points.txt
art_dl-0.2.7.dist-info/WHEEL
art_dl-0.2.7.dist-info/METADATA
art_dl-0.2.7.dist-info/RECORD
