Metadata-Version: 2.1
Name: art-dl
Version: 0.2.7
Summary: Artworks downloader
Home-page: https://github.com/istudyatuni/artworks-downloader
Author: Ilia
Author-email: istudyatuni@gmail.com
Requires-Python: >=3.10,<4.0
Classifier: Environment :: Console
Classifier: Operating System :: OS Independent
Classifier: Programming Language :: Python :: 3
Classifier: Programming Language :: Python :: 3.10
Classifier: Programming Language :: Python :: 3.11
Classifier: Programming Language :: Python :: 3
Requires-Dist: aiofiles (>=0.8.0,<0.9.0)
Requires-Dist: aiohttp (>=3.8.1,<4.0.0)
Requires-Dist: aiohttp-socks[asyncio] (>=0.7.1,<0.8.0)
Requires-Dist: lxml (>=4.8.0,<5.0.0)
Requires-Dist: platformdirs (>=2.5.2,<3.0.0)
Project-URL: Repository, https://github.com/istudyatuni/artworks-downloader
Project-URL: Tracker, https://github.com/istudyatuni/artworks-downloader/issues
